django_pwned/__init__.py
django_pwned/api.py
django_pwned/apps.py
django_pwned/exceptions.py
django_pwned/validators.py
django_pwned/locale/fa/LC_MESSAGES/django.mo
django_pwned/locale/fa/LC_MESSAGES/django.po
django_pwned-1.2.2.dist-info/LICENSE.txt
django_pwned-1.2.2.dist-info/METADATA
django_pwned-1.2.2.dist-info/WHEEL
django_pwned-1.2.2.dist-info/top_level.txt
django_pwned-1.2.2.dist-info/RECORD
